kmh_gpu_monitor/__init__.py
kmh_gpu_monitor/__main__.py
kmh_gpu_monitor/copy_id.py
kmh_gpu_monitor/kmh_gpu_monitor.py
kmh_gpu_monitor-0.2.3.dist-info/LICENSE
kmh_gpu_monitor-0.2.3.dist-info/METADATA
kmh_gpu_monitor-0.2.3.dist-info/WHEEL
kmh_gpu_monitor-0.2.3.dist-info/top_level.txt
kmh_gpu_monitor-0.2.3.dist-info/RECORD
