Metadata-Version: 2.1
Name: kmh-gpu-monitor
Version: 0.2.3
Summary: Multi-server GPU monotoring tools
Home-page: https://github.com/kairos03/kairos-smi
Author: Eunseop Shin
Author-email: kairos9603@gmail.com
License: MIT
Classifier: Programming Language :: Python :: 3
Classifier: License :: OSI Approved :: MIT License
Classifier: Operating System :: OS Independent
License-File: LICENSE
